osmapipy2/OsmApi.py
osmapipy2/__init__.py
osmapipy2/errors.py
osmapi_py2-2.0.0.dist-info/LICENSE.txt
osmapi_py2-2.0.0.dist-info/METADATA
osmapi_py2-2.0.0.dist-info/WHEEL
osmapi_py2-2.0.0.dist-info/top_level.txt
osmapi_py2-2.0.0.dist-info/RECORD
